pokemonNames-0.1.0.dist-info/RECORD
pokemonNames-0.1.0.dist-info/metadata.json
pokemonNames-0.1.0.dist-info/DESCRIPTION.rst
pokemonNames-0.1.0.dist-info/top_level.txt
pokemonNames-0.1.0.dist-info/WHEEL
pokemonNames-0.1.0.dist-info/METADATA
pokemonNames/names.list
pokemonNames/__init__.py
pokemonNames/pokemonNames.py
