Metadata-Version: 1.1
Name: pokemonNames
Version: 0.1.0
Summary: Generate pokemon names.
Home-page: https://github.com/darkowlzz/pokemonNames
Author: Sunny (darkowlzz)
Author-email: indiasuny000@gmail.com
License: GPL
Keywords: pokemon
Platform: UNKNOWN
Classifier: Development Status :: 2 - Pre-Alpha
Classifier: Intended Audience :: Developers
Classifier: Natural Language :: English
Classifier: Programming Language :: Python :: 2.7
